mcp_wyze_server/__init__.py
mcp_wyze_server/server.py
mcp_wyze_server-0.1.2.dist-info/METADATA
mcp_wyze_server-0.1.2.dist-info/WHEEL
mcp_wyze_server-0.1.2.dist-info/entry_points.txt
mcp_wyze_server-0.1.2.dist-info/licenses/LICENSE
mcp_wyze_server-0.1.2.dist-info/RECORD
