Metadata-Version: 2.4
Name: mcp-wyze-server
Version: 0.1.2
Summary: MCP server for controlling Wyze smart home devices
Project-URL: Homepage, https://github.com/aldilaff/mcp-wyze-server
Project-URL: Repository, https://github.com/aldilaff/mcp-wyze-server
Project-URL: Issues, https://github.com/aldilaff/mcp-wyze-server/issues
Project-URL: Documentation, https://github.com/aldilaff/mcp-wyze-server#readme
Author-email: Faisal Aldilaijan <github@faisal.software>
Maintainer-email: Faisal Aldilaijan <github@faisal.software>
License: MIT
License-File: LICENSE
Keywords: home-automation,iot,mcp,smart-home,wyze
Classifier: Development Status :: 4 - Beta
Classifier: Intended Audience :: Developers
Classifier: License :: OSI Approved :: MIT License
Classifier: Programming Language :: Python :: 3
Classifier: Programming Language :: Python :: 3.13
Classifier: Topic :: Home Automation
Classifier: Topic :: Software Development :: Libraries :: Python Modules
Requires-Python: >=3.13
Requires-Dist: mcp[cli]>=1.12.2
Requires-Dist: wyze-sdk-aldilaff>=2.2.1
